tenda/__init__.py
tenda-0.0.8.dist-info/LICENSE
tenda-0.0.8.dist-info/METADATA
tenda-0.0.8.dist-info/WHEEL
tenda-0.0.8.dist-info/top_level.txt
tenda-0.0.8.dist-info/RECORD
