Metadata-Version: 2.1
Name: tenda
Version: 0.0.8
Summary: Unofficial Tenda Model N301 API
Home-page: https://github.com/talhabalaj/tenda-n301-api-python
Author: Talha Balaj
Author-email: talhabalaj@gmail.com
License: UNKNOWN
Platform: UNKNOWN
Classifier: Programming Language :: Python :: 3
Classifier: License :: OSI Approved :: GNU General Public License v3 (GPLv3)
Classifier: Operating System :: OS Independent
Requires-Dist: requests
